memu/__init__.py
memu/audio.py
memu/audio_fhir.py
memu/drug_interaction.py
memu/drug_interaction_fhir.py
memu/extraction.py
memu/extraction_fhir.py
memu/hcpcs.py
memu/hcpcs_fhir.py
memu/icd10.py
memu/icd10_fhir.py
memu/summarization.py
memu/summarization_fhir.py
memu/tests/__init__.py
memu/tests/test_audio.py
memu/tests/test_audio_fhir.py
memu/tests/test_auth.py
memu/tests/test_drug_interaction.py
memu/tests/test_drug_interaction_fhir.py
memu/tests/test_extraction.py
memu/tests/test_extraction_fhir.py
memu/tests/test_hcpcs.py
memu/tests/test_hcpcs_fhir.py
memu/tests/test_icd10.py
memu/tests/test_icd10_fhir.py
memu/tests/test_summarization.py
memu/tests/test_summarization_fhir.py
medical_multimodal-0.0.16.dist-info/LICENSE
medical_multimodal-0.0.16.dist-info/METADATA
medical_multimodal-0.0.16.dist-info/WHEEL
medical_multimodal-0.0.16.dist-info/top_level.txt
medical_multimodal-0.0.16.dist-info/RECORD
