Metadata-Version: 2.1
Name: medical-multimodal
Version: 0.0.16
Summary: MeMu SDK for medical-focused tasks with FHIR compliance.
Home-page: https://github.com/Medical-Multimodal/MeMu_Package.git
Author: Juan Fernando Lavieri
Author-email: juan.f.lavieri@memu.life
License: MeMu SDK License
Classifier: Programming Language :: Python :: 3
Classifier: License :: Other/Proprietary License
Classifier: Operating System :: OS Independent
Requires-Python: >=3.6
License-File: LICENSE
Requires-Dist: requests
Requires-Dist: openai
Requires-Dist: psycopg2
Requires-Dist: fhir.resources
